example/__init__.py
example/customize_env.py
example/training_DDPG.py
power_network_rl/__init__.py
power_network_rl/DRL_algorithms/Agent.py
power_network_rl/DRL_algorithms/DDPG.py
power_network_rl/DRL_algorithms/PPO.py
power_network_rl/DRL_algorithms/SAC.py
power_network_rl/DRL_algorithms/TD3.py
power_network_rl/DRL_algorithms/__init__.py
power_network_rl/DRL_algorithms/utility.py
power_network_rl/benckmark_algorithms/__init__.py
power_network_rl/data_manager/__init__.py
power_network_rl/data_manager/data_manager.py
power_network_rl/data_sources/__init__.py
power_network_rl/data_sources/network_data/__init__.py
power_network_rl/data_sources/network_data/node_123/Lines_123.csv
power_network_rl/data_sources/network_data/node_123/Nodes_123.csv
power_network_rl/data_sources/network_data/node_25/Lines_25.csv
power_network_rl/data_sources/network_data/node_25/Nodes_25.csv
power_network_rl/data_sources/network_data/node_34/Lines_34.csv
power_network_rl/data_sources/network_data/node_34/Nodes_34.csv
power_network_rl/data_sources/network_data/node_69/Lines_69.csv
power_network_rl/data_sources/network_data/node_69/Nodes_69.csv
power_network_rl/data_sources/time_series_data/25_node_time_series.csv
power_network_rl/data_sources/time_series_data/34_node_time_series.csv
power_network_rl/data_sources/time_series_data/__init__.py
power_network_rl/environments/Component_Battery.py
power_network_rl/environments/Environment_Integrated.py
power_network_rl/environments/__init__.py
power_network_rl/utility/Power_Flow.py
power_network_rl/utility/__init__.py
power_network_rl/utility/grid.py
power_network_rl/utility/numbarize.py
power_network_rl/utility/utils.py
tests/123_node_network_powerflow_test.py
tests/25_node_network_powerflow_test.py
tests/34_node_network_powerflow_test.py
tests/69_node_network_powerflow_test.py
tests/__init__.py
tests/data_manager_test.py
RL_ADN-0.1.3.dist-info/License
RL_ADN-0.1.3.dist-info/METADATA
RL_ADN-0.1.3.dist-info/WHEEL
RL_ADN-0.1.3.dist-info/top_level.txt
RL_ADN-0.1.3.dist-info/RECORD
