Metadata-Version: 2.1
Name: RL-ADN
Version: 0.1.3
Summary: RL-ADN: A Benchmark Framework for DRL-based Battery Energy Arbitrage in Distribution Networks
Home-page: https://github.com/ShengrenHou/RL-ADN
Author: Hou Shengren, Gao Shuyi, Pedro Vargara
Author-email: houshengren97@gmail.com
License: MIT
Keywords: DRL energy arbitrage
License-File: License
